Compression/__init__.py
Compression/PyTorch/__init__.py
Compression/tensorflow_v2/__init__.py
MakGraph/__init__.py
McUtils/__init__.py
config/__init__.py
test/__init__.py
ModelCompresLight-1.0.0.dist-info/METADATA
ModelCompresLight-1.0.0.dist-info/WHEEL
ModelCompresLight-1.0.0.dist-info/top_level.txt
ModelCompresLight-1.0.0.dist-info/RECORD
