Metadata-Version: 2.1
Name: ModelCompresLight
Version: 1.0.0
Summary: Lighter Model Ensemble
Home-page: UNKNOWN
Author: CO-AI Team
Author-email: 710783785@qq.com
License: MIT
Platform: UNKNOWN
Requires-Python: >=3.6.2
Requires-Dist: thop
